angularhostpagetemplate/__init__.py
angularhostpagetemplate/backend.py
angularhostpagetemplate/engine.py
angularhostpagetemplate/tool/__init__.py
angularhostpagetemplate/tool/pulldist.py
django_angular_host_page_template_backend-0.3.1.dist-info/LICENSE.md
django_angular_host_page_template_backend-0.3.1.dist-info/METADATA
django_angular_host_page_template_backend-0.3.1.dist-info/WHEEL
django_angular_host_page_template_backend-0.3.1.dist-info/top_level.txt
django_angular_host_page_template_backend-0.3.1.dist-info/RECORD
