Metadata-Version: 2.1
Name: django-angular-host-page-template-backend
Version: 0.3.1
Summary: Angular Host-page Template Backend and Utility for Django
License: MIT License
Platform: UNKNOWN
Classifier: Development Status :: 5 - Production/Stable
Classifier: Intended Audience :: Developers
Classifier: License :: OSI Approved :: MIT License
Classifier: Programming Language :: Python :: 3.7
Classifier: Framework :: Django :: 3.2
License-File: LICENSE.md
